Metadata-Version: 2.4
Name: rgkit_py3
Version: 1.2.0
Summary: Game Engine for Robot Game
Home-page: https://github.com/saavedra29/rgkit_py3
Maintainer: Aristeidis Tomaras
Maintainer-email: arisgold29@gmail.com
License: Unlicense
License-File: LICENSE
License-File: AUTHORS
Dynamic: description
Dynamic: home-page
Dynamic: license
Dynamic: license-file
Dynamic: maintainer
Dynamic: maintainer-email
Dynamic: summary
